README.md
setup.py
invprob/__init__.py
invprob/general.py
invprob/optim.py
invprob/prox.py
invprob/signal.py
invprob/sparse.py
invprob/wavelet.py
invprob/wavelet_old.py
invprob.egg-info/PKG-INFO
invprob.egg-info/SOURCES.txt
invprob.egg-info/dependency_links.txt
invprob.egg-info/requires.txt
invprob.egg-info/top_level.txt