Metadata-Version: 2.1
Name: invprob
Version: 0.0.14
Summary: A package containing useful functions for solving inverse problems
Home-page: https://github.com/Guillaume-Garrigos/invprob/
Author: Guillaume Garrigos
Author-email: guillaume.garrigos@lpsm.paris
License: MIT
Platform: UNKNOWN
Classifier: Programming Language :: Python :: 3
Classifier: License :: OSI Approved :: MIT License
Classifier: Operating System :: OS Independent
Requires-Python: >=3.7
